AUTHORS.rst
ChangeLog.rst
LICENSE
MANIFEST.in
README.rst
setup.py
django_kewl/__init__.py
django_kewl.egg-info/PKG-INFO
django_kewl.egg-info/SOURCES.txt
django_kewl.egg-info/dependency_links.txt
django_kewl.egg-info/requires.txt
django_kewl.egg-info/top_level.txt
django_kewl/templatetags/__init__.py
django_kewl/templatetags/markwhat.py
django_kewl/templatetags/meta_head.py
django_kewl/templatetags/search.py