Metadata-Version: 1.1
Name: django-kewl
Version: 2014.10.26
Summary: Set of Django kewl utilities & helpers & highly used/needed stuff.
Home-page: https://github.com/Alir3z4/django-kewl
Author: Alireza Savand
Author-email: alireza.savand@gmail.com
License: BSD
Platform: OS Independent
Classifier: Development Status :: 5 - Production/Stable
Classifier: Environment :: Web Environment
Classifier: Intended Audience :: Developers
Classifier: Operating System :: OS Independent
Classifier: Framework :: Django
Classifier: Programming Language :: Python
Classifier: Programming Language :: Python :: 2
Classifier: Programming Language :: Python :: 2.6
Classifier: Programming Language :: Python :: 2.7
Classifier: Topic :: Software Development
Classifier: License :: OSI Approved :: BSD License
